{
    "Completed courses": {
        "Semseter 1": [
            "104031",
            "234114",
            "114071",
            "000022",
            "134058"
        ],
        "Semester 2": [
            "104032",
            "104166",
            "094412",
            "234124"
        ]
    },
    "Suggested courses": {
        "Semester 3": [
            "234141",
            "234129",
            "044252",
            "234125",
            "324033",
            "104285"
        ],
        "Semester 4": [
            "234218",
            "234118",
            "234292",
            "236319",
            "236781",
            "114075"
        ],
        "Semester 5": [
            "234247",
            "234123",
            "104134",
            "236363",
            "000011"
        ],
        "Semester 6": [
            "104293",
            "094423",
            "236343",
            "000021",
            "000031"
        ],
        "Semester 7": [
            "236360",
            "236334",
            "236501",
            "236342",
            "236719",
            "000012"
        ],
        "Semester 8": [
            "234313",
            "000023"
        ]
    }
}