{
    "Completed courses": {
        "Semester 1": [
            "234114",
            "234129",
            "124120",
            "094222",
            "000011",
            "000021"
        ],
        "Semester 2": [
            "104031",
            "104166",
            "234124",
            "044252"
        ]
    },
    "Suggested courses": {
        "Semester 3": [
            "104032",
            "114071",
            "094412",
            "234118"
        ],
        "Semester 4": [
            "234141",
            "104134",
            "234292",
            "234313"
        ],
        "Semester 5": [
            "324033",
            "234125",
            "104285",
            "236363"
        ],
        "Semester 6": [
            "234218",
            "236360",
            "134058",
            "236319",
            "236342",
            "104293",
            "000022",
            "000031"
        ],
        "Semester 7": [
            "234247",
            "234123",
            "134020",
            "236334",
            "000012",
            "000023"
        ],
        "Semester 8": [
            "236343",
            "236501",
            "236719"
        ]
    }
}