{
    "Completed courses": {
        "Semseter 1": [
            "104166",
            "234114",
            "000022",
            "134058",
            "094222",
            "096411"
        ],
        "Semester 2": [
            "104031",
            "234124",
            "234129",
            "044252",
            "114071"
        ],
        "Semester 3": [
            "104032",
            "094412",
            "234118",
            "234292",
            "104134"
        ],
        "Semester 4": [
            "234141",
            "234125",
            "236360",
            "104285",
            "236363",
            "236342"
        ]
    },
    "Suggested courses": {
        "Semester 5": [
            "234218",
            "236319",
            "236523",
            "124120",
            "000011",
            "000021",
            "000031"
        ],
        "Semester 6": [
            "234247",
            "324033",
            "236501",
            "125801",
            "000012",
            "000023"
        ],
        "Semester 7": [
            "236343",
            "234123",
            "236334",
            "236719",
            "236309",
            "234313"
        ]
    }
}