{
    "Completed courses": {
        "Semseter 1": [
            "104031",
            "234114",
            "114071",
            "324033",
            "000022",
            "134058"
        ],
        "Semester 2": [
            "104032",
            "104166",
            "094412",
            "234124",
            "234129"
        ],
        "Semester 3": [
            "234141",
            "044252",
            "234292",
            "104134",
            "104293",
            "104285"
        ],
        "Semester 4": [
            "234218",
            "234118",
            "234125",
            "236363",
            "124120",
            "104135"
        ]
    },
    "Suggested courses": {
        "Semester 5": [
            "234247",
            "234123",
            "236360",
            "236319",
            "236334",
            "134020"
        ],
        "Semester 6": [
            "236343",
            "236703",
            "236309",
            "236781",
            "000011",
            "000021",
            "000031"
        ],
        "Semester 7": [
            "236272",
            "000012",
            "000023"
        ]
    }
}