{
    "Completed courses": {
        "Semester 1": [
            "234114",
            "234129",
            "324033",
            "094222",
            "096411",
            "000022",
            "000031"
        ],
        "Semester 2": [
            "104031",
            "104166",
            "114071",
            "044252"
        ],
        "Semester 3": [
            "104032",
            "234124",
            "094412",
            "104134",
            "234292"
        ],
        "Semester 4": [
            "234125",
            "234141",
            "234118",
            "104285",
            "236342",
            "236363"
        ],
        "Semester 5": [
            "234218",
            "124120",
            "134058",
            "236309",
            "236319",
            "000011",
            "000021"
        ],
        "Semester 6": [
            "234247",
            "234123",
            "236360",
            "236334",
            "236501",
            "000023"
        ]
    },
    "Suggested courses": {
        "Semester 7": [
            "236343",
            "114052",
            "134020",
            "234313",
            "000012"
        ]
    }
}